rpackutils/__init__.py
rpackutils/command.py
rpackutils/config.py
rpackutils/depsmanager.py
rpackutils/graph.py
rpackutils/json_serializer.py
rpackutils/license.py
rpackutils/packinfo.py
rpackutils/provider.py
rpackutils/rbasepackages.py
rpackutils/reposconfig.py
rpackutils/tree.py
rpackutils/utils.py
rpackutils/cli/__init__.py
rpackutils/cli/cliBioc.py
rpackutils/cli/cliClone.py
rpackutils/cli/cliConfigCheck.py
rpackutils/cli/cliDepsGraph.py
rpackutils/cli/cliDownload.py
rpackutils/cli/cliInstall.py
rpackutils/cli/cliMirror.py
rpackutils/cli/cliMran.py
rpackutils/cli/cliQuery.py
rpackutils/cli/cliScan.py
rpackutils/providers/__init__.py
rpackutils/providers/artifactory.py
rpackutils/providers/bioconductor.py
rpackutils/providers/cran.py
rpackutils/providers/localrepository.py
rpackutils/providers/nexus.py
rpackutils/providers/renvironment.py
tests/__init__.py
tests/test_artifactory.py
tests/test_bioconductor.py
tests/test_config.py
tests/test_cran.py
tests/test_depsmanager.py
tests/test_graph.py
tests/test_license.py
tests/test_localrepository.py
tests/test_packinfo.py
tests/test_renvironment.py
tests/test_reposconfig.py
tests/test_tree.py
tests/test_version.py
RPackUtils-0.1.9.dist-info/LICENSE
RPackUtils-0.1.9.dist-info/METADATA
RPackUtils-0.1.9.dist-info/WHEEL
RPackUtils-0.1.9.dist-info/entry_points.txt
RPackUtils-0.1.9.dist-info/top_level.txt
RPackUtils-0.1.9.dist-info/RECORD
